ytapinvl/__init__.py
ytapinvl/buyrole.py
ytapinvl/cli.py
ytapinvl/config.py
ytapinvl/harga.py
ytapinvl/me.py
ytapinvl/utils.py
ytapinvl-1.1.6.dist-info/licenses/LICENSE
ytapinvl-1.1.6.dist-info/METADATA
ytapinvl-1.1.6.dist-info/WHEEL
ytapinvl-1.1.6.dist-info/entry_points.txt
ytapinvl-1.1.6.dist-info/top_level.txt
ytapinvl-1.1.6.dist-info/RECORD
