Metadata-Version: 2.4
Name: ytapinvl
Version: 1.1.6
Summary: CLI resmi YT API by Nauval — cek role, harga, dan beli role via QRIS
Author: M. Nauval Sayyid Abdillah
License: MIT
Project-URL: Homepage, https://ytdlpyton.nvlgroup.my.id
Project-URL: Repository, https://github.com/nauvalunesa/ytapinvl
Keywords: ytapi,qris,nauval,fastapi,midtrans
Requires-Python: >=3.8
License-File: LICENSE
Requires-Dist: requests>=2.31.0
Dynamic: license-file
